{
  "saved_at": "2026-06-23T13:21:11",
  "rows": [
    {
      "row_id": "doc_emp_tawuchao_damlau_id_general_תעודת_זהות",
      "employee_id": "emp_tawuchao_damlau",
      "employee_name": "דמלאו טווצ'או",
      "category": "id",
      "title": "תעודת זהות",
      "month_key": "",
      "file_name": "תעודת זהות (2).pdf",
      "drive_file_id": "1YK-2XiZDcoL4oLAqscax3CJAdAOBXOJl",
      "drive_url": "https://drive.google.com/file/d/1YK-2XiZDcoL4oLAqscax3CJAdAOBXOJl/view?usp=drivesdk",
      "updated_at": "2026-05-03T22:46:28"
    },
    {
      "row_id": "doc_emp_tawuchao_damlau_pension_2026-04_אישור_קופה_פעילה_מיטב",
      "employee_id": "emp_tawuchao_damlau",
      "employee_name": "דמלאו טווצ'או",
      "category": "pension",
      "title": "אישור קופה פעילה - מיטב",
      "month_key": "2026-04",
      "file_name": "ApprovalActiveFund.pdf",
      "drive_file_id": "1_hw466q3s0w-3GUgyo4v62BRkRPYAPaV",
      "drive_url": "https://drive.google.com/file/d/1_hw466q3s0w-3GUgyo4v62BRkRPYAPaV/view?usp=drivesdk",
      "updated_at": "2026-05-03T22:46:23"
    },
    {
      "row_id": "doc_emp_tawuchao_damlau_contract_2026-04_הסכם_העסקה_גלובלי",
      "employee_id": "emp_tawuchao_damlau",
      "employee_name": "דמלאו טווצ'או",
      "category": "contract",
      "title": "הסכם העסקה גלובלי",
      "month_key": "2026-04",
      "file_name": "טווצ׳או - הסכם העסקה גלובלי.pdf",
      "drive_file_id": "1mda0Y9A4TDclnmN3tZPSfGWGRM0l-FF-",
      "drive_url": "https://drive.google.com/file/d/1mda0Y9A4TDclnmN3tZPSfGWGRM0l-FF-/view?usp=drivesdk",
      "updated_at": "2026-05-03T22:46:18"
    },
    {
      "row_id": "f8e8c9f93f774a11bfe52ffeb93530cb",
      "employee_id": "emp_tawuchao_damlau",
      "employee_name": "דמלאו טווצ'או",
      "category": "sick_note",
      "title": "WhatsApp Image 2026-05-06 at 13.28.51",
      "month_key": "2026-05",
      "file_name": "WhatsApp Image 2026-05-06 at 13.28.51.jpeg",
      "drive_file_id": "1VStt-PDtQ659I12X7-zY6EeNYLv8vOpE",
      "drive_url": "https://drive.google.com/file/d/1VStt-PDtQ659I12X7-zY6EeNYLv8vOpE/view?usp=drivesdk",
      "updated_at": "2026-06-03T11:41:01"
    },
    {
      "row_id": "006a5e38dc0940eebf0efd4b9c92bb31",
      "employee_id": "emp_tawuchao_damlau",
      "employee_name": "דמלאו טווצ'או",
      "category": "sick_note",
      "title": "WhatsApp Image 2026-05-31 at 22.10.00",
      "month_key": "2026-05",
      "file_name": "WhatsApp Image 2026-05-31 at 22.10.00.jpeg",
      "drive_file_id": "1MT5fX-VJalrp-to7CeH4aKeKEnav6zKu",
      "drive_url": "https://drive.google.com/file/d/1MT5fX-VJalrp-to7CeH4aKeKEnav6zKu/view?usp=drivesdk",
      "updated_at": "2026-06-03T11:37:43"
    }
  ]
}